sales_report/__init__.py
sales_report/main.py
sales_report/report.py
sales_report_by_podpivas-0.1.0.dist-info/METADATA
sales_report_by_podpivas-0.1.0.dist-info/WHEEL
sales_report_by_podpivas-0.1.0.dist-info/top_level.txt
sales_report_by_podpivas-0.1.0.dist-info/RECORD
